meter_reader/__init__.py
meter_reader/client.py
meter_reader/gateway.py
meter_reader/utc.py
meter_reader-1.1.2.dist-info/DESCRIPTION.rst
meter_reader-1.1.2.dist-info/METADATA
meter_reader-1.1.2.dist-info/RECORD
meter_reader-1.1.2.dist-info/WHEEL
meter_reader-1.1.2.dist-info/entry_points.txt
meter_reader-1.1.2.dist-info/metadata.json
meter_reader-1.1.2.dist-info/top_level.txt
