Metadata-Version: 2.0
Name: meter-reader
Version: 1.1.2
Summary: Client Library for retreiving smart meter data from an Eagle Energy Gateway
Home-page: https://github.com/eman/meter_reader
Author: Emmanuel Levijarvi
Author-email: emansl@gmail.com
License: BSD
Keywords: energy electricity smartmeter HAN
Platform: UNKNOWN
Classifier: Development Status :: 4 - Beta
Classifier: Intended Audience :: Developers
Classifier: Topic :: Home Automation
Classifier: Topic :: Utilities
Classifier: License :: OSI Approved :: BSD License
Classifier: Operating System :: OS Independent
Classifier: Programming Language :: Python :: 2.7
Classifier: Programming Language :: Python :: 3
